unifi_respondd/config.py
unifi_respondd/logger.py
unifi_respondd/respondd_client.py
unifi_respondd/unifi_client.py
unifi_respondd-0.0.8.dist-info/LICENSE
unifi_respondd-0.0.8.dist-info/METADATA
unifi_respondd-0.0.8.dist-info/WHEEL
unifi_respondd-0.0.8.dist-info/top_level.txt
unifi_respondd-0.0.8.dist-info/RECORD
