Metadata-Version: 2.1
Name: unifi-respondd
Version: 0.0.8
Summary: A tool to display Unifi APs on Freifunk maps.
Home-page: http://packages.python.org/unifi_respondd
Author: Annika Wickert
Author-email: aw@awlnx.space
License: GPLv3
Keywords: Unifi Freifunk
Platform: UNKNOWN
License-File: LICENSE
Requires-Dist: pyunifi (==2.21)
Requires-Dist: geopy (==2.2.0)
Requires-Dist: pyyaml (==6.0)
Requires-Dist: dataclasses-json (==0.5.6)
